pokemon_pinyin/__init__.py
pokemon_pinyin/commands.py
pokemon_pinyin/draw.py
pokemon_pinyin/pokemon.py
pokemon_pinyin/searcher.py
pokemon_pinyin/utils.py
pokemon_pinyin/data/chinese.simhei.ttf
pokemon_pinyin/data/searcher.json
pokemon_pinyin-0.0.2.dist-info/METADATA
pokemon_pinyin-0.0.2.dist-info/WHEEL
pokemon_pinyin-0.0.2.dist-info/entry_points.txt
pokemon_pinyin-0.0.2.dist-info/top_level.txt
pokemon_pinyin-0.0.2.dist-info/RECORD
