Metadata-Version: 2.1
Name: pokemon_pinyin
Version: 0.0.2
Summary: Learn pinyin with pokemon
Author-email: fcfangcc <fcfangcc@163.com>
Requires-Python: >=3.10
Requires-Dist: lxml ~=5.2.2
Requires-Dist: requests ~=2.32.3
Requires-Dist: pypinyin ~=0.51.0
Requires-Dist: pillow ~=10.4.0
Requires-Dist: click
Requires-Dist: platformdirs
